{"emailIncorrect":"อีเมลที่คุณกรอกไม่ถูกต้อง โปรดลองอีกครั้ง","passwordMismatch":"รหัสผ่านในช่องรหัสผ่านและช่องยืนยันรหัสผ่านไม่ตรงกัน โปรดลองใหม่อีกครั้ง","mobileEmpty":"โปรดกรอกหมายเลขโทรศัพท์มือถือของคุณ แล้วลองใหม่อีกครั้ง","lastNameEmpty":"โปรดกรอกนามสกุลของคุณ แล้วลองใหม่อีกครั้ง","firstNameEmpty":"โปรดกรอกชื่อจริงของคุณ แล้วลองใหม่อีกครั้ง","confirmPasswordEmpty":"โปรดยืนยันรหัสผ่านของคุณในช่องยืนยันรหัสผ่าน แล้วลองใหม่อีกครั้ง","passwordEmpty":"โปรดกรอกรหัสผ่านในช่องรหัสผ่าน แล้วลองใหม่อีกครั้ง","emailEmpty":"โปรดกรอกอีเมลลงในช่องอีเมล แล้วลองใหม่อีกครั้ง","weakPasswordSubmit":"รหัสผ่านของคุณไม่ปลอดภัยเพียงพอ โปรดลองใหม่อีกครั้ง","registerCompletedTitle":"สมัครสมาชิกสำเร็จ","registerCompletedContext":"การสมัครสมาชิกเสร็จสิ้น ยินดีต้อนรับสู่ Worklabs","Register":"สมัครสมาชิก","email":"อีเมล","password":"รหัสผ่าน","confirm your password":"ยืนยันรหัสผ่าน","firstname":"ชื่อจริง","lastname":"นามสกุล","mobile number":"หมายเลขโทรศัพท์มือถือ","Enter your email...":"กรอกอีเมลของคุณ...","Create your password...":"สร้างรหัสผ่านของคุณ...","Confirm your password...":"ยืนยันรหัสผ่านที่คุณสร้าง...","Enter your firstname...":"กรอกชื่อจริงของคุณ...","Enter your lastname...":"กรอกนามสกุลของคุณ...","Enter your mobile number...":"กรอกหมายเลขโทรศัพท์มือถือของคุณ..."}